pytaco.py
pytaco-1.0.2.dist-info/entry_points.txt
pytaco-1.0.2.dist-info/LICENSE
pytaco-1.0.2.dist-info/WHEEL
pytaco-1.0.2.dist-info/METADATA
pytaco-1.0.2.dist-info/RECORD
