Metadata-Version: 1.2
Name: pytaco
Version: 1.0.2
Summary: How many tacos for a meetup?
Home-page: https://github.com/Mariatta/pytaco
License: UNKNOWN
Author: Mariatta Wijaya
Author-email: mariatta.wijaya@gmail.com
Maintainer: Mariatta Wijaya
Maintainer-email: mariatta.wijaya@gmail.com
Requires-Python: >=3.6
Classifier: Programming Language :: Python :: 3.6
Classifier: Intended Audience :: Developers
Classifier: License :: OSI Approved :: Apache Software License
